[
    {
        "id":1,
        "name":"Story Book",
        "title":"hii ,lorem i am book thise book ios story book",
        "price":0,
        "category":"free",
        "image":""

    },
    {
        "id":2,
        "name":"Story Book",
        "title":"hii ,lorem i am book thise book ios story book",
        "price":0,
        "category":"free",
        "image":""

    },
    {
        "id":3,
        "name":"Story Book",
        "title":"hii ,lorem i am book thise book ios story book",
        "price":20,
        "category":"entertainment",
        "image":""

    },
    {
        "id":4,
        "name":"Story Book",
        "title":"hii ,lorem i am book thise book ios story book",
        "price":100,
        "category":"sports",
        "image":""

    },
    {
        "id":5,
        "name":"Story Book",
        "title":"hii ,lorem i am book thise book ios story book",
        "price":0,
        "category":"free",
        "image":""

    },
    {
        "id":6,
        "name":"Story Book",
        "title":"hii ,lorem i am book thise book ios story book",
        "price":0,
        "category":"free",
        "image":""

    },
    {
        "id":6,
        "name":"Story Book",
        "title":"hii ,lorem i am book thise book ios story book",
        "price":0,
        "category":"free",
        "image":""

    },
    {
        "id":6,
        "name":"Story Book",
        "title":"hii ,lorem i am book thise book ios story book",
        "price":0,
        "category":"free",
        "image":""

    },
    {
        "id":6,
        "name":"Story Book",
        "title":"hii ,lorem i am book thise book ios story book",
        "price":0,
        "category":"free",
        "image":""

    },
    {
        "id":6,
        "name":"Story Book",
        "title":"hii ,lorem i am book thise book ios story book",
        "price":0,
        "category":"food",
        "image":""

    }
]